IceBearUtils/__init__.py
IceBearUtils/setup.py
IceBearUtils/zwfw/__init__.py
IceBearUtils/zwfw/autodownload/__init__.py
IceBearUtils/zwfw/autodownload/run.py
icebearutils-1.0.2.dist-info/METADATA
icebearutils-1.0.2.dist-info/RECORD
icebearutils-1.0.2.dist-info/WHEEL
icebearutils-1.0.2.dist-info/top_level.txt
